parallel_augustus/__init__.py
parallel_augustus/checks.py
parallel_augustus/cli.py
parallel_augustus/pipeline.py
parallel_augustus-1.0.2.dist-info/LICENSE.md
parallel_augustus-1.0.2.dist-info/METADATA
parallel_augustus-1.0.2.dist-info/WHEEL
parallel_augustus-1.0.2.dist-info/entry_points.txt
parallel_augustus-1.0.2.dist-info/top_level.txt
parallel_augustus-1.0.2.dist-info/RECORD
