Metadata-Version: 2.1
Name: parallel-augustus
Version: 1.0.2
Summary: Simple wrapper around Augustus to bring faster restitution times
Home-page: https://github.com/bistace/parallel_augustus
Download-URL: https://github.com/bistace/parallel_augustus
Author: ['Benjamin Istace']
License: CeCILL
Keywords: bioinformatics,genomics,genome,annotation,augustus
Classifier: Development Status :: 4 - Beta
Classifier: Intended Audience :: Science/Research
Classifier: Topic :: Scientific/Engineering :: Bio-Informatics
Classifier: License :: OSI Approved :: CEA CNRS Inria Logiciel Libre License, version 2.1 (CeCILL-2.1)
Classifier: Programming Language :: Python :: 3.8
License-File: LICENSE.md
Requires-Dist: biopython
Requires-Dist: coloredlogs
